sea_serpent_python-0.0.1.dist-info/METADATA
sea_serpent_python-0.0.1.dist-info/WHEEL
sea_serpent/__init__.py
sea_serpent/sea_serpent.cpython-37m-x86_64-linux-gnu.so
sea_serpent_python-0.0.1.dist-info/RECORD
