Metadata-Version: 2.1
Name: sea-serpent-python
Version: 0.0.1
